{
  "IcoMoonType": "selection",
  "icons": [
    {
      "icon": {
        "paths": [
          "M1022.2 120.7l-120.4-120.4-512 512 512 512 120.4-120.4-390.8-391.6 390.8-391.6z",
          "M1.3 904.1l120.6 120.2 511.1-512.8-512.8-511.2-120.2 120.6 391.4 391-390.1 392.2z"
        ],
        "attrs": [
          {},
          {}
        ],
        "isMulticolor": false,
        "isMulticolor2": false,
        "grid": 0,
        "tags": [
          "close"
        ]
      },
      "attrs": [
        {},
        {}
      ],
      "properties": {
        "order": 21,
        "id": 17,
        "name": "close",
        "prevSize": 64,
        "code": 59664
      },
      "setIdx": 1,
      "setId": 0,
      "iconIdx": 0
    },
    {
      "icon": {
        "paths": [
          "M828 120.4l-120.4-120.4-512 512 512 512 120.4-120.4-390.8-391.6z"
        ],
        "attrs": [
          {}
        ],
        "isMulticolor": false,
        "isMulticolor2": false,
        "grid": 0,
        "tags": [
          "back"
        ]
      },
      "attrs": [
        {}
      ],
      "properties": {
        "order": 20,
        "id": 16,
        "name": "back",
        "prevSize": 64,
        "code": 59663
      },
      "setIdx": 1,
      "setId": 0,
      "iconIdx": 1
    },
    {
      "icon": {
        "paths": [
          "M878 929.997c-14.6 18.6-37 27.8-60.8 27.8h-610c-23.8 0-45-9.2-59.6-27.8-15.8-17.2-21.2-41-18.6-63.6 22.4-144.2 145.6-250 292.4-250h181.2c142.8 0 266 101.8 291 243.4l1.4 5.2c4 22.6-1.2 46.4-17 65v0zM960 847.997c-31.8-172-181.2-297.6-355.8-297.6h-182.6c-178.6 0-329.4 129.6-358.6 305.6-14.6 88.6 54.2 168 142.8 168h611.2c90 0 158.8-82 142.8-170.6v-5.4z",
          "M321 422c53 53 121.8 79.4 190.6 79.4 66.2 0 133.6-25.2 185.2-74l2.6-2.6c91.2-87.4 100.6-228.8 19.8-326.8-54.2-64.8-131-98-207.8-98v66c60.8 0 117.8 26.4 156.2 74 58.2 70.2 51.6 174.6-14.6 236.8l-2.6 2.6c-38.4 35.8-87.4 55.6-139 55.6-54.2 0-105.8-21.2-142.8-59.6l-1.4-1.4c-62.2-62.2-67.4-160-14.6-230.2 38.4-50.2 96.6-78 160-78v-66c-79.4 0-158.8 34.4-211.6 103.2-74 95.2-66.2 231.6 19.8 317.6v1.4z"
        ],
        "attrs": [
          {},
          {}
        ],
        "isMulticolor": false,
        "isMulticolor2": false,
        "grid": 0,
        "tags": [
          "profile"
        ]
      },
      "attrs": [
        {},
        {}
      ],
      "properties": {
        "order": 17,
        "id": 15,
        "name": "profile",
        "prevSize": 64,
        "code": 59648
      },
      "setIdx": 1,
      "setId": 0,
      "iconIdx": 2
    },
    {
      "icon": {
        "paths": [
          "M719.6 509.2l-282.2-195.2c-8.8-6.6-32.2-6.6-34 18.2v390.6c2 24.8 25.8 25.2 34 18.2l282.2-195.2c7.4-4.6 17.4-22.8 0-36.6v0zM447 681v-307.2l221.6 153.6-221.6 153.6z",
          "M512 0c-282.4 0-512 229.6-512 512s229.6 512 512 512 512-229.6 512-512-229.6-512-512-512v0zM512 980.4c-258.2 0-468.4-210-468.4-468.4s210.2-468.4 468.4-468.4 468.4 210 468.4 468.4-210.2 468.4-468.4 468.4v0z"
        ],
        "attrs": [
          {},
          {}
        ],
        "isMulticolor": false,
        "isMulticolor2": false,
        "grid": 0,
        "tags": [
          "play"
        ]
      },
      "attrs": [
        {},
        {}
      ],
      "properties": {
        "order": 2,
        "id": 14,
        "name": "play",
        "prevSize": 64,
        "code": 59649
      },
      "setIdx": 1,
      "setId": 0,
      "iconIdx": 3
    },
    {
      "icon": {
        "paths": [
          "M512 1024.2c57.8 0 105-47.2 105-105h-210c0 57.6 46.8 105 105 105v0zM827 709v-262.6c0-161.2-86.2-296.2-236.4-331.8v-35.8c0-43.6-35.2-78.8-78.8-78.8s-78.8 35.2-78.8 78.8v35.8c-150.4 35.8-236 170.2-236 331.8v262.6l-105.2 105v52.6h840.2v-52.6l-105-105z"
        ],
        "attrs": [
          {}
        ],
        "isMulticolor": false,
        "isMulticolor2": false,
        "grid": 0,
        "tags": [
          "notification"
        ]
      },
      "attrs": [
        {}
      ],
      "properties": {
        "order": 4,
        "id": 13,
        "name": "notification",
        "prevSize": 64,
        "code": 59650
      },
      "setIdx": 1,
      "setId": 0,
      "iconIdx": 4
    },
    {
      "icon": {
        "paths": [
          "M255.4 662c-3 0-5.6-0.6-7.8-2l-86.4-47-86.6 47.2c-4.6 2.8-11.8 2.4-16.6-1.2-4.8-3.8-7-10-5.6-15.8l22.8-90.8-70.6-70.4c-4.4-4.4-5.8-10.8-3.4-16.6s7.8-9.6 14-9.6l87-2 46.4-86.4v-1.2l1-0.8 0.8-1.6 1.8-0.2 2.2-1.8h0.8c0.4-0.2 1-0.4 1.4-0.6 1.4-0.4 2.8-0.8 4.4-0.8h1.2c0.6 0 1.4 0.2 2.4 0.2h0.4l1.4 0.4c1.6 0.6 3 1.4 4.4 2.2l0.6 0.6c1.2 1 2 2 3 3.4l0.8 1.2 45.6 85 87 2c6 0.2 11.6 3.8 13.8 9.6v0c2.2 5.8 1 12.2-3.4 16.6l-70.8 70.2 22 88c1 2 1.6 4.4 1.6 6.6-0.2 8.8-7.2 15.6-15.6 15.6zM66 644.2c-0.2 0-0.2 0.2 0 0v0zM256.4 644.2v0c0 0 0 0 0 0zM22 473.6l73.4 72.8-23.8 94.6 89.6-48.8 89.6 48.8-23.8-94.6 73.4-72.8-91-2-48.2-89.8-48.2 89.8-91 2zM307 473.8c0 0 0 0 0 0v0zM15.4 473.8v0c0 0 0 0 0 0zM305.2 469c0 0-0.2 0 0 0v0z",
          "M610.4 662c-3 0-5.6-0.6-7.8-2l-86.4-47-86.6 47.2c-4.8 2.8-11.8 2.4-16.6-1.2-5-3.8-7-10-5.6-16l22.8-90.8-70.8-70.2c-4.4-4.4-5.6-11-3.4-16.6 2.4-5.8 7.8-9.4 14-9.6l87-2 46.4-86.4v-1l1-0.8 1-1.8 1.6-0.2 2.4-2h0.8c0.4-0.2 1-0.4 1.4-0.6l1.8-0.4c0.8-0.2 1.8-0.2 2.8-0.4h1.2c0.6 0 1.4 0.2 2.2 0.2h0.4l1.4 0.4c1.6 0.6 3 1.2 4.4 2.2l0.8 0.6c1 1 2 2 3 3.4l1 1.8 45.4 84.6 87 2c6 0.2 11.6 3.8 13.8 9.6v0c2.2 5.8 0.8 12.2-3.6 16.6l-70.6 70.2 22 88c1 2 1.6 4.4 1.6 6.6-0.4 8.8-7.4 15.6-15.8 15.6zM425 647.4v0c0 0 0 0 0 0zM420.8 644.2c0 0 0 0.2 0 0v0zM611.4 644.2v0c0 0 0 0 0 0zM376.8 473.6l73.4 72.8-23.8 94.6 89.6-48.8 89.6 48.8-23.6-94.4 73.4-73-91-2-48.2-89.8-48.2 89.8-91.2 2zM370.4 473.8v0c0 0 0 0 0 0zM662 473.8c0 0 0 0 0 0v0zM660 469c0 0 0 0 0 0v0z",
          "M957 662c-3 0-5.6-0.6-7.8-2l-86.4-47.2-86.6 47.2c-4.8 2.8-12 2.4-16.8-1.4-4.8-3.6-7-9.8-5.4-15.8l22.8-90.8-70.6-70c-4.4-4.4-5.8-11-3.4-16.6 2.2-5.6 7.8-9.4 14-9.6l87-2 46.4-86.4v-1.2l1-0.8 0.8-1.6 1.6-0.2 2.2-1.8h1c0.4-0.2 0.8-0.4 1.4-0.6l1.8-0.4c0.8-0.2 1.8-0.2 2.8-0.4h1.2c0.6 0 1.4 0.2 2.2 0.2h0.4l1.4 0.4c1.6 0.6 3 1.2 4.2 2.2l2 1.8c0.6 0.6 1.2 1.4 1.8 2.2l0.6 1 45.8 85.2 87 2c6 0.2 11.6 3.8 13.8 9.6v0.2c2.2 5.8 0.8 12.2-3.6 16.6l-70.6 70.2 22 87.8c1 2 1.6 4.4 1.6 6.6-0.2 8.8-7.2 15.6-15.6 15.6zM767.4 644.2c0 0 0 0.2 0 0v0zM958 644.2v0c0 0 0 0 0 0zM723.6 473.6l73.4 72.8-23.8 94.6 89.6-48.8 89.6 48.8-23.8-94.6 73.4-72.8-91-2-48.2-90-48.2 90-91 2zM1008.6 473.8c0 0 0 0 0 0v0zM717 473.8v0c0 0 0 0 0 0zM1006.6 469c0 0 0 0 0 0v0z"
        ],
        "attrs": [
          {},
          {},
          {}
        ],
        "isMulticolor": false,
        "isMulticolor2": false,
        "grid": 0,
        "tags": [
          "score"
        ]
      },
      "attrs": [
        {},
        {},
        {}
      ],
      "properties": {
        "order": 5,
        "id": 12,
        "name": "score",
        "prevSize": 64,
        "code": 59651
      },
      "setIdx": 1,
      "setId": 0,
      "iconIdx": 5
    },
    {
      "icon": {
        "paths": [
          "M391 705.227c167.2 0 302.8-135.8 302.8-303.2s-135.6-303.2-302.8-303.2c-167.2 0-302.8 135.8-302.8 303.2s135.4 303.2 302.8 303.2zM391 9.827c216.4 0 391.8 175.6 391.8 392.4 0 86.6-28.2 166.8-75.6 231.6l0.4-0.4 296.4 296.8-0.6 0.8c12 8.2 19.8 22 19.8 37.6 0 25.2-20.4 45.8-45.6 45.8-14.2 0-26.6-6.6-35-16.8l-1 1-298.8-296 0.4-0.4c-68.2 57.4-156 92.2-252.2 92.2-216.4 0-391.8-175.6-391.8-392.4s175.4-392.2 391.8-392.2z"
        ],
        "attrs": [
          {}
        ],
        "isMulticolor": false,
        "isMulticolor2": false,
        "grid": 0,
        "tags": [
          "search"
        ]
      },
      "attrs": [
        {}
      ],
      "properties": {
        "order": 6,
        "id": 11,
        "name": "search",
        "prevSize": 64,
        "code": 59652
      },
      "setIdx": 1,
      "setId": 0,
      "iconIdx": 6
    },
    {
      "icon": {
        "paths": [
          "M511.4-0.6c-282.6 0-512 229.4-512 512s229.4 512 512 512 512-229.4 512-512c0-282.6-229.4-512-512-512v0zM409 767.4l-256-256 72.2-72.2 183.8 183.2 388.6-388.6 72.2 72.8-460.8 460.8z"
        ],
        "attrs": [
          {}
        ],
        "isMulticolor": false,
        "isMulticolor2": false,
        "grid": 0,
        "tags": [
          "check"
        ]
      },
      "attrs": [
        {}
      ],
      "properties": {
        "order": 7,
        "id": 10,
        "name": "check",
        "prevSize": 64,
        "code": 59653
      },
      "setIdx": 1,
      "setId": 0,
      "iconIdx": 7
    },
    {
      "icon": {
        "paths": [
          "M535.8 716.4v-171.8c43.4 16 93 45.4 93 95.2 0 54.2-59 71.4-93 76.6zM394.2 411.8c0-51.4 44.6-79 93-86v154.2c-39.6-10.6-93-29.4-93-68.2zM535.8 493.2v-167.4c51.8 7.8 85.4 39 86.2 39.6 9.6 9.2 25 9 34.4-0.6s9-25.2-0.6-34.4c-2.2-2-48-45.2-120-53.4v-44.4c0-13.4-11-24.4-24.4-24.4s-24.4 11-24.4 24.4v44.4c-83.4 9.2-141.6 63-141.6 135.2 0 80 92 106 141.6 118.6v185.2c-37.6-8.2-90.6-30-110.8-50.2-9.6-9.6-25-9.6-34.4 0-9.6 9.6-9.6 25 0 34.4 29.2 29.2 97.4 56.8 145.2 65.2v40c0 13.4 11 24.4 24.4 24.4s24.4-11 24.4-24.4v-39c62.6-7.4 141.8-44 141.8-126.2 0-66.2-50.2-118-141.8-147z",
          "M511.4 975.842c-251 0-463.2-212.2-463.2-463.2s212.2-463.2 463.2-463.2 463.2 212.2 463.2 463.2-212 463.2-463.2 463.2zM511.4 0.642c-277.6 0-512 234.4-512 512s234.4 512 512 512 512-234.4 512-512-234.4-512-512-512z"
        ],
        "attrs": [
          {},
          {}
        ],
        "isMulticolor": false,
        "isMulticolor2": false,
        "grid": 0,
        "tags": [
          "value"
        ]
      },
      "attrs": [
        {},
        {}
      ],
      "properties": {
        "order": 8,
        "id": 9,
        "name": "value",
        "prevSize": 64,
        "code": 59654
      },
      "setIdx": 1,
      "setId": 0,
      "iconIdx": 8
    },
    {
      "icon": {
        "paths": [
          "M195.6 711.8c126.6 38.4 258.6 57.8 392.8 57.8 78.2 0 156.8-6.8 233.6-20.2 53.6-9.2 107.2-22 159.2-37.8v-506.8c-52-15.8-105.6-28.4-159.6-37.8-76.6-13.2-155-20-233.2-20-134.2 0-266.2 19.4-392.8 57.8v507h-0zM588.4 811.4c-143.8 0-285.4-21.6-420.6-64.4-8.8-2.8-14.8-10.8-14.8-20v-537.6c0-9 6-17.2 14.8-20 135.4-42.8 277-64.4 420.8-64.4 80.6 0 161.4 7 240.6 20.6 61 10.6 121.6 25.4 180.2 43.8 8.8 2.8 14.8 10.8 14.8 20v537.6c0 9.2-6 17.2-14.8 20-58.6 18.6-119 33.2-179.6 43.6-79.6 13.8-160.6 20.8-241.4 20.8v0z",
          "M783.4 786.8c-11.8 0-21.4-9.4-21.4-21v-615.2c0-11.6 9.6-21 21.4-21s21.4 9.4 21.4 21v615.2c0 11.6-9.6 21-21.4 21z",
          "M380.2 786.8c-11.8 0-21.4-9.4-21.4-21v-615.2c0-11.6 9.6-21 21.4-21s21.4 9.4 21.4 21v615.2c0 11.6-9.6 21-21.4 21z",
          "M1023.8 270.8v-42h-870.8v42z",
          "M1002.6 270.8h-828.4c-11.8 0-21.4-9.4-21.4-21s9.6-21 21.4-21h828.2c11.8 0 21.4 9.4 21.4 21s-9.4 21-21.2 21z",
          "M1023.8 412.4v-41.8h-870.8v41.8z",
          "M1002.6 412.4h-828.4c-11.8 0-21.4-9.4-21.4-21s9.6-21 21.4-21h828.2c11.8 0 21.4 9.4 21.4 21s-9.4 21-21.2 21z",
          "M1023.8 554.2v-42h-870.8v42z",
          "M1002.6 554.2h-828.4c-11.8 0-21.4-9.4-21.4-21s9.6-21 21.4-21h828.2c11.8 0 21.4 9.4 21.4 21s-9.4 21-21.2 21z",
          "M1023.8 687.6v-41.8h-870.8v41.8z",
          "M1002.6 687.6h-828.4c-11.8 0-21.4-9.4-21.4-21s9.6-21 21.4-21h828.2c11.8 0 21.4 9.4 21.4 21s-9.4 21-21.2 21z",
          "M21.2 679.8c-11.8 0-21.4-9.4-21.4-21v-52c0-40.2 41.6-72.8 92.6-72.8h71.2c11.8 0 21.4 9.4 21.4 21s-9.6 21-21.4 21h-71c-29.4 0-50 16.4-50 31v52c0 11.6-9.6 20.8-21.4 20.8z",
          "M100.6 576c-11.8 0-21.4-9.4-21.4-21v-82c0-11.6 9.6-21 21.4-21s21.4 9.4 21.4 21v82c0 11.6-9.6 21-21.4 21z",
          "M279.4 919.8c-11.8 0-21.4-9.4-21.4-21v-144.6c0-11.6 9.6-21 21.4-21s21.4 9.4 21.4 21v144.6c0 11.6-9.6 21-21.4 21z",
          "M897.4 919.8c-11.8 0-21.4-9.4-21.4-21v-144.6c0-11.6 9.6-21 21.4-21s21.4 9.4 21.4 21v144.6c0 11.6-9.6 21-21.4 21z"
        ],
        "attrs": [
          {},
          {},
          {},
          {},
          {},
          {},
          {},
          {},
          {},
          {},
          {},
          {},
          {},
          {},
          {}
        ],
        "isMulticolor": false,
        "isMulticolor2": false,
        "grid": 0,
        "tags": [
          "cellar"
        ]
      },
      "attrs": [
        {},
        {},
        {},
        {},
        {},
        {},
        {},
        {},
        {},
        {},
        {},
        {},
        {},
        {},
        {}
      ],
      "properties": {
        "order": 9,
        "id": 8,
        "name": "cellar",
        "prevSize": 64,
        "code": 59655
      },
      "setIdx": 1,
      "setId": 0,
      "iconIdx": 9
    },
    {
      "icon": {
        "paths": [
          "M511.6 475.315c132.4 0 256 123.4 256 256 0 132.4-123.4 256-256 256s-256-123.4-256-256c0-132.6 123.4-256 256-256zM511.6 438.715c-154.6 0-292.6 137.8-292.6 292.6 0 154.6 137.8 292.6 292.6 292.6s292.4-138 292.4-292.6c0-154.8-137.8-292.6-292.4-292.6z",
          "M511.6 566.8c84.6 0 164.6 80 164.6 164.6s-80 164.6-164.6 164.6-164.6-80-164.6-164.6c0-84.8 79.8-164.6 164.6-164.6zM511.6 530.2c-106.8 0-201 94.4-201 201.2s94.2 201 201 201 201-94.4 201-201.2-94.2-201-201-201z",
          "M511.6 684.4l12.6 27.4c3 6.2 9.2 10.2 16 10.2l25.2 1.2-20.6 18.2c-5.6 4.8-7.8 12.4-5.8 19.4l5.8 22.8-25.2-13.8c-5.8-3-12.8-2.4-18.2 1.2l-24 13.8 5.8-27.4c1.8-6.6-0.6-13.8-5.8-18.2l-20.6-16 29.8-3.4c6.4-0.6 12-4.4 14.8-10.2l10.2-25.2zM508 620.4c-6.2 1.2-11.4 5.4-13.8 11.4l-22.8 53.8-61.8 5.8c-10 1-17.4 9.8-16.4 20 0.4 4.6 2.6 9 6.2 12l45.6 36.6-12.6 58.2c-2.8 9.6 2.6 19.8 12.4 22.8 5 1.4 10.6 0.8 15-2.2l50.2-30.8 54.8 29.8c9 4.8 20 1.2 24.8-7.6 2-4 2.6-8.6 1.6-13l-14.8-54.8 46.8-40c7.6-6.6 8.4-18.2 1.8-25.8-3-3.6-7.4-5.8-12-6.2l-60.6-3.4-25.2-54.8c-2.8-8.2-10.8-13-19.2-11.8v0z",
          "M359.6 365.6c-7.8 2.6-13 10-12.6 18.2v108.6c-0.2 10 8 18.4 18 18.6s18.4-8 18.6-18v-90.8h256v90.2c-0.2 10 8 18.4 18 18.6s18.4-8 18.6-18v-109.2c0-10-8.2-18.2-18.2-18.2h-292.8c-1.8-0.2-3.8-0.2-5.6 0z",
          "M103.6-0.085c-9.6 3.4-14.6 13.8-11.2 23.4 0.6 1.4 1.2 2.8 2 4.2l254.8 384c4.6 9 15.8 12.4 24.6 7.6 9-4.6 12.4-15.8 7.6-24.6-0.4-0.8-1-1.6-1.6-2.4l-236.2-355.6h176l177.2 248c6 8.2 17.4 10 25.8 4 8.2-6 10-17.6 4-25.8l-182.8-256c-3.6-4.4-9.2-7-14.8-6.8h-219.6c-2-0.2-4-0.2-5.8 0z",
          "M688.6-0.085c-3.6 1.2-6.8 3.6-9.2 6.8l-256 365.6c-6 8.2-4.2 19.8 4 25.8s19.8 4.2 25.8-4l250.2-357.6h176l-236.4 355.4c-7.4 6.8-7.8 18.4-1 25.8s18.4 7.8 25.8 1c2.2-2 3.8-4.6 4.8-7.4l256-384c5-8.8 2-20-6.6-25-2.6-1.4-5.4-2.2-8.2-2.4h-219.4c-2-0.2-3.8-0.2-5.8 0z"
        ],
        "attrs": [
          {},
          {},
          {},
          {},
          {},
          {}
        ],
        "isMulticolor": false,
        "isMulticolor2": false,
        "grid": 0,
        "tags": [
          "featured"
        ]
      },
      "attrs": [
        {},
        {},
        {},
        {},
        {},
        {}
      ],
      "properties": {
        "order": 10,
        "id": 7,
        "name": "featured",
        "prevSize": 64,
        "code": 59656
      },
      "setIdx": 1,
      "setId": 0,
      "iconIdx": 10
    },
    {
      "icon": {
        "paths": [
          "M599.8 361.027c-21.4 0-43-4.4-63.4-13.4l-8.8-4-3.2-9.2c-3.6-10.4-5.8-21.8-7-35l-0.2 3.6c-1.4 12-3.6 22-6.6 31.2l-3 9.2-8.8 4c-56.6 25.2-122.8 14.4-168.8-27.2-45.8-42-62.6-107-42.8-165.6l3-9.2 8.8-4c33.8-15 72.4-17.2 107.6-6.8 9-57.4 46.8-107.2 101-131l8.8-3.8 8.8 3.8c54.4 24 92.2 74 101 131.4 35.8-11 74.8-9.2 109.4 6.2l8.8 4 3 9.2c19.8 58.8 3 123.8-42.8 165.6-29 27-66.6 41-104.8 41zM563.4 311.027c38.6 13.2 81.4 4.4 111.8-23.2 30.4-27.8 43-69.8 33.4-109.4-30-10.2-63.6-7-91.6 8.8l-35.4 20 2.6-40.6c0.2-1.6 0.2-3.2 0.2-4.6 0-47.6-26.4-91.2-68-113.4-41.6 22.2-68 65.6-68 113.4l1.2 42.8-33.6-18.4c-27.6-15.2-60.8-18-90.2-8-9.6 39.6 3 81.6 33.4 109.4 30.4 27.6 73.4 36.2 111.8 23.2 0.8-3.6 1.4-7.4 2-11.8v-48.6c0-24.2 19.8-44 44-44s44 19.8 44 44v45.8c0.6 4.8 1.4 9.8 2.4 14.6z",
          "M512 613.227c-61.8 0-112.2-50.4-112.2-112.2 0-62 50.4-112.2 112.2-112.2s112.2 50.4 112.2 112.2c0 62-50.4 112.2-112.2 112.2zM512 432.827c-37.6 0-68.2 30.6-68.2 68.2s30.6 68.2 68.2 68.2c37.6 0 68.2-30.6 68.2-68.2-0.2-37.6-30.6-68.2-68.2-68.2z",
          "M294.4 613.227c-61.8 0-112.2-50.4-112.2-112.2 0-62 50.4-112.4 112.2-112.4s112.2 50.4 112.2 112.4c0.2 62-50.2 112.2-112.2 112.2zM294.4 432.827c-37.6 0-68.2 30.6-68.2 68.2s30.6 68.2 68.2 68.2c37.6 0 68.2-30.6 68.2-68.2s-30.4-68.2-68.2-68.2z",
          "M391 806.627c-61.8 0-112.2-50.4-112.2-112.2 0-62 50.4-112.2 112.2-112.2s112.2 50.4 112.2 112.2c0.2 61.8-50.2 112.2-112.2 112.2zM391 626.227c-37.6 0-68.2 30.6-68.2 68.2s30.6 68.2 68.2 68.2c37.6 0 68.2-30.6 68.2-68.2 0.2-37.6-30.4-68.2-68.2-68.2z",
          "M512 1024.227c-61.8 0-112.2-50.4-112.2-112.2 0-62 50.4-112.2 112.2-112.2 62 0 112.2 50.4 112.2 112.2s-50.4 112.2-112.2 112.2zM512 843.627c-37.6 0-68.2 30.6-68.2 68.2s30.6 68.2 68.2 68.2 68.2-30.6 68.2-68.2c0-37.6-30.6-68.2-68.2-68.2z",
          "M632.8 806.627c-61.8 0-112.2-50.4-112.2-112.2 0-62 50.4-112.2 112.2-112.2 30 0 58.2 11.6 79.4 33 21.2 21.2 32.8 49.4 32.8 79.4 0.2 61.6-50.2 112-112.2 112zM632.8 626.227c-37.6 0-68.2 30.6-68.2 68.2s30.6 68.2 68.2 68.2c37.6 0 68.2-30.6 68.2-68.2 0-18.2-7-35.4-20-48.2-12.8-13-30-20-48.2-20z",
          "M729.4 613.227c-62 0-112.2-50.4-112.2-112.2 0-62 50.4-112.4 112.2-112.4s112.2 50.4 112.2 112.4c0 62-50.2 112.2-112.2 112.2zM729.4 432.827c-37.6 0-68.2 30.6-68.2 68.2s30.6 68.2 68.2 68.2c37.6 0 68.2-30.6 68.2-68.2s-30.6-68.2-68.2-68.2z"
        ],
        "attrs": [
          {},
          {},
          {},
          {},
          {},
          {},
          {}
        ],
        "isMulticolor": false,
        "isMulticolor2": false,
        "grid": 0,
        "tags": [
          "feed"
        ]
      },
      "attrs": [
        {},
        {},
        {},
        {},
        {},
        {},
        {}
      ],
      "properties": {
        "order": 11,
        "id": 6,
        "name": "feed",
        "prevSize": 64,
        "code": 59657
      },
      "setIdx": 1,
      "setId": 0,
      "iconIdx": 11
    },
    {
      "icon": {
        "paths": [
          "M714.2 374h72.2c9.8 0 17.8-8 17.8-17.6v0-102.8c0-9.8 8-17.6 17.6-17.6h100.6c9.8 0 17.6-8 17.6-17.8v0-60.8c0-9.8-8-17.6-17.6-17.6h-100.8c-9.8 0-17.6-8-17.6-17.6v0-104.8c0-9.8-8-17.6-17.6-17.6h-72c-9.8 0-17.6 8-17.6 17.6v0 104.6c0 9.8-8 17.6-17.6 17.6h-100.6c-9.8 0-17.6 8-17.6 17.6v60.6c0 9.8 8 17.6 17.6 17.6h100.6c9.8 0 17.6 8 17.6 17.6v103c-0.2 9.8 7.6 17.8 17.4 18v0z",
          "M928.4 890.43l-199.6-199.2c36.4-56.8 55.8-122.8 55.8-190.4h-74.2c-0.6 156-127.6 281.8-283.6 281.2s-281.8-127.8-281.2-283.6c0.6-155.6 127.2-281.4 282.8-281.2v-75c-197.4 0-357.4 160.2-357.4 357.6s160.2 357.4 357.6 357.4c67.8 0 134.4-19.4 191.6-55.8 1.2 2.6 199.6 199.6 199.6 199.6 14.4 14.6 34 22.8 54.4 22.8 20.4 0.2 40.2-8 54.4-22.8 30.4-29.4 31.4-77.8 2-108.4-0.8-0.8-1.6-1.6-2.2-2.2z"
        ],
        "attrs": [
          {},
          {}
        ],
        "isMulticolor": false,
        "isMulticolor2": false,
        "grid": 0,
        "tags": [
          "advanced"
        ]
      },
      "attrs": [
        {},
        {}
      ],
      "properties": {
        "order": 12,
        "id": 5,
        "name": "advanced",
        "prevSize": 64,
        "code": 59658
      },
      "setIdx": 1,
      "setId": 0,
      "iconIdx": 12
    },
    {
      "icon": {
        "paths": [
          "M591.4 872.549l-79-47.4 394.6-97.8 60 145.2h-375.6zM64.2 847.349l284-72.6 161 97.8h-457.6l12.6-25.2zM143.2 651.749l151.6 91.6-211.6 53.6 60-145.2zM458.8 730.549c3.2 6.4 9.4 9.4 19 9.4 6.4 0 15.8-3.2 19-9.4 3.2-3.2 22-37.8 44.2-85.2h328.2l19 47.4-429.2 104.2-252.6-151.6h208.4c25 47.4 44 82 44 85.2v0zM477.8 152.949c82 0 151.6 69.4 151.6 151.6 0 53.6-60 189.4-113.6 296.8-12.6 28.4-25.2 50.6-37.8 72.6-53.6-104.2-151.6-299.8-151.6-369.4-0.2-82.2 69.2-151.6 151.4-151.6v0zM903.8 613.749c-3.2-6.4-9.4-12.6-19-12.6h-322c50.6-101 107.4-233.6 107.4-296.8 0-107.4-85.2-195.6-192.6-195.6s-192.6 88.4-192.6 195.6c0 63.2 60 195.6 107.4 296.8h-258.8c-9.4 0-15.8 6.4-19 12.6l-113.6 271.6c-3.2 6.4 0 12.6 3.2 19s9.4 9.4 19 9.4h978.6c6.4 0 12.6-3.2 19-9.4 3.2-6.4 3.2-12.6 3.2-19l-120.2-271.6z",
          "M477.8 358.227c-28.4 0-50.6-22-50.6-50.6 0-25.2 22-47.4 50.6-47.4s50.6 22 50.6 50.6c-0.2 25.2-22.2 47.4-50.6 47.4zM569.2 310.827c0-50.6-41-91.6-91.6-91.6s-91.6 41-91.6 91.6 41 91.6 91.6 91.6 91.6-41.2 91.6-91.6z"
        ],
        "attrs": [
          {},
          {}
        ],
        "isMulticolor": false,
        "isMulticolor2": false,
        "grid": 0,
        "tags": [
          "location"
        ]
      },
      "attrs": [
        {},
        {}
      ],
      "properties": {
        "order": 13,
        "id": 4,
        "name": "location",
        "prevSize": 64,
        "code": 59659
      },
      "setIdx": 1,
      "setId": 0,
      "iconIdx": 13
    },
    {
      "icon": {
        "paths": [
          "M784.2 803h-545.2c-16.2 0-29.6 13.4-29.6 29.6s13.4 29.6 29.6 29.6h545c16.2 0 29.6-13.4 29.6-29.6s-13.2-29.6-29.4-29.6z",
          "M964.2 888.215c-22.8 54.8-74 89-133.4 89h-638.2c-59.6 0-110.8-34.2-133.6-89.2s-10.8-115.4 31.4-157.6l250-250v-37.4h137c10.8 0 19.8-9 19.8-19.8v-4c0-10.8-9-19.8-19.8-19.8h-137v-98h137c10.8 0 19.8-9 19.8-19.8v-4c0-10.8-9-19.8-19.8-19.8h-137v-91.8h137c10.8 0 19.8-9 19.8-19.8v-4c0-10.8-9-19.8-19.8-19.8h-137v-62h342.8v418.2l250.2 252.2c41.8 42.2 53.8 102.6 30.8 157.4zM967.4 697.015l-236.6-238v-398.6h63.4c17 0 30.8-13.8 30.8-30.8s-13.8-30.8-30.8-30.8h-542.6c-17 0-30.8 13.8-30.8 30.8s13.8 30.8 30.8 30.8h40.8v400.2l-236 236c-56 56-72 136.4-41.8 209.6 30.4 73.2 98.4 118.8 177.8 118.8h638.2c79.2 0 147.2-45.4 177.6-118.4 30.6-73 15-153.4-40.8-209.6z"
        ],
        "attrs": [
          {},
          {}
        ],
        "isMulticolor": false,
        "isMulticolor2": false,
        "grid": 0,
        "tags": [
          "analysis"
        ]
      },
      "attrs": [
        {},
        {}
      ],
      "properties": {
        "order": 14,
        "id": 3,
        "name": "analysis",
        "prevSize": 64,
        "code": 59660
      },
      "setIdx": 1,
      "setId": 0,
      "iconIdx": 14
    },
    {
      "icon": {
        "paths": [
          "M806.6 987.2h-56.4c3.8-18.8 7.4-37.8 10.8-56.4h61.4c-5 18.8-10.2 37.6-15.8 56.4v0zM612 987.2c1.4-19 2.8-37.8 4-56.4h107.4c-3.4 18.8-7.2 37.6-11 56.4h-100.4zM449.2 987.2c-1.4-19-2.8-37.8-4-56.4h133.8c-1.2 18.6-2.6 37.4-4 56.4h-125.8zM300.6 930.8h107.4c1.2 18.6 2.6 37.4 4 56.4h-100.4c-3.8-18.8-7.6-37.8-11-56.4v0zM201.6 930.8h61.4c3.4 18.8 7 37.6 10.8 56.4h-56.4c-5.6-18.8-10.8-37.6-15.8-56.4v0zM176.6 115.8h671l13.6 81h-698.4l13.8-81zM217.4 36.8h56.4c-2.8 14.2-5.6 28.2-8.2 42.2h-60.2c3.8-14.2 7.8-28.2 12-42.2v0zM412 36.8c-1 13.6-2 27.6-3 42.2h-105.8c2.6-14 5.4-28 8.4-42.2h100.4zM574.8 36.8c1 13.6 2 27.6 3 42.2h-131.8c1-14.4 2-28.4 3-42.2h125.8zM720.8 79h-105.8c-1-14.4-2-28.4-3-42.2h100.4c3 14.2 5.6 28.2 8.4 42.2v0zM818.6 79h-60.2c-2.6-14-5.4-28-8.2-42.2h56.4c4.2 14 8.2 28 12 42.2v0zM399.6 776h-122c-20.8-180.2-20.2-362.4 1.6-542.4h121c-8 180-8.2 362.2-0.6 542.4v0zM586.8 233.6c8 180 8.4 362.4 0.6 542.4h-150.8c-7.6-180.2-7.4-362.4 0.6-542.4h149.6zM744.8 233.6c21.8 180 22.4 362.4 1.8 542.4h-122c7.6-180.2 7.4-362.4-0.6-542.4h120.8zM853 233.6c31.4 180 32.2 362.4 2.4 542.4h-71.8c20.4-180.2 19.8-362.4-1.6-542.4h71zM171 233.6h71c-21.6 180-22 362.4-1.6 542.4h-71.8c-30-180-29.2-362.4 2.4-542.4v0zM847.4 893.8h-670.8l-13.6-81h698.2l-13.8 81zM892.6 778.8c29.6-181.4 29-365.2-2.2-546.8 2.6-1.2 4.8-2.8 6.8-5 3.6-4.2 5-9.6 4.2-15l-19.8-117.8c-1.4-8.8-9.2-15.4-18.2-15.4h-6.2c-5.8-22-12.2-44.2-18.8-65.8-2.4-7.8-9.6-13-17.8-13h-617c-8.2 0-15.4 5.2-17.6 13-6.6 21.8-13 43.8-18.8 65.8h-6.2c-9 0-16.8 6.4-18.2 15.4l-19.8 117.8c-1 5.4 0.6 10.8 4.2 15 1.8 2.2 4.2 3.8 6.8 5-31.2 181.4-32 365.2-2.2 546.8-1.6 1-3.2 2.4-4.6 3.8-3.6 4.2-5 9.6-4.2 15l19.8 117.8c1.4 8.8 9.2 15.4 18.2 15.4h2.6c6.8 26.8 14.4 53.6 22.6 80.2 2.4 7.8 9.6 13 17.6 13h616.6c8.2 0 15.4-5.2 17.8-13 8.2-26.6 15.6-53.4 22.6-80.2h2.6c9 0 16.8-6.4 18.2-15.4l19.8-117.8c1-5.4-0.6-10.8-4.2-15-1.4-1.6-3-2.8-4.6-3.8v0z"
        ],
        "attrs": [
          {}
        ],
        "isMulticolor": false,
        "isMulticolor2": false,
        "grid": 0,
        "tags": [
          "barrel"
        ]
      },
      "attrs": [
        {}
      ],
      "properties": {
        "order": 15,
        "id": 2,
        "name": "barrel",
        "prevSize": 64,
        "code": 59661
      },
      "setIdx": 1,
      "setId": 0,
      "iconIdx": 15
    },
    {
      "icon": {
        "paths": [
          "M507.009 390.037c-10.8 0-19.6-8.8-21.8-19.6-4.4-32.6 4.4-65.4 15.2-91.6 13-32.6 13-65.4 0-82.8-6.6-11-4.4-24 6.6-30.6s24-4.4 30.6 6.6c30.6 43.6 13 100.2 4.4 124.2-8.8 21.8-15.2 45.8-13 67.6 2.2 10.8-6.6 24-17.4 24-2.4 2.2-2.4 2.2-4.6 2.2z",
          "M337.109 390.037c-10.8 0-19.6-8.8-21.8-19.6-4.4-32.6 4.4-65.4 15.2-91.6 13-32.6 13-65.4 0-82.8-6.6-11-4.4-24 6.6-30.6s24-4.4 30.6 6.6c30.6 43.6 13 100.2 4.4 124.2-8.8 21.8-15.2 45.8-13 67.6 2.2 10.8-6.6 24-17.4 24-2.4 2.2-4.6 2.2-4.6 2.2z",
          "M670.464 390.037c-10.8 0-19.6-8.8-21.8-19.6-4.4-32.6 4.4-63.2 15.2-91.6 13-32.6 13-65.4 0-82.8-6.6-11-4.4-24 6.6-30.6s24-4.4 30.6 6.6c30.4 43.6 13 100.2 4.4 124.2-8.8 21.8-15.2 45.8-13 67.6 2.2 10.8-6.6 24-17.4 24-2.4 2.2-4.6 2.2-4.6 2.2z",
          "M123.582 529.546c15.2 141.6 183 252.8 387.8 252.8s372.6-111.2 387.8-252.8h-775.6zM511.382 825.746c-239.6 0-433.6-141.6-433.6-318.2 0-13 8.8-21.8 21.8-21.8h821.4c13 0 21.8 8.8 21.8 21.8 2.2 174.4-191.8 318.2-431.4 318.2v0z",
          "M1006 529.427h-89.4c-13 0-21.8-8.8-21.8-21.8s8.8-21.8 21.8-21.8h89.4c13 0 21.8 8.8 21.8 21.8-0.2 13.2-8.8 21.8-21.8 21.8z",
          "M114.8 529.427h-89.4c-13 0-21.8-8.8-21.8-21.8s8.8-21.8 21.8-21.8h89.4c13 0 21.8 8.8 21.8 21.8 0 13.2-8.8 21.8-21.8 21.8z"
        ],
        "attrs": [
          {},
          {},
          {},
          {},
          {},
          {}
        ],
        "isMulticolor": false,
        "isMulticolor2": false,
        "grid": 0,
        "tags": [
          "pairings"
        ]
      },
      "attrs": [
        {},
        {},
        {},
        {},
        {},
        {}
      ],
      "properties": {
        "order": 16,
        "id": 1,
        "name": "pairings",
        "prevSize": 64,
        "code": 59662
      },
      "setIdx": 1,
      "setId": 0,
      "iconIdx": 16
    }
  ],
  "height": 1024,
  "metadata": {
    "name": "vinoapp"
  },
  "preferences": {
    "showGlyphs": true,
    "showCodes": true,
    "showQuickUse": true,
    "showQuickUse2": true,
    "showSVGs": true,
    "fontPref": {
      "prefix": "icon-",
      "metadata": {
        "fontFamily": "vinoapp",
        "majorVersion": 1,
        "minorVersion": 0
      },
      "metrics": {
        "emSize": 1024,
        "baseline": 6.25,
        "whitespace": 50
      },
      "embed": false,
      "noie8": false,
      "ie7": false,
      "showVersion": true,
      "showMetadata": true,
      "showMetrics": true,
      "showSelector": true,
      "selector": ""
    },
    "imagePref": {
      "prefix": "icon-",
      "png": true,
      "useClassSelector": true,
      "color": 0,
      "bgColor": 16777215
    },
    "historySize": 50,
    "gridSize": 16
  }
}